datadec/__init__.py
datadec/constants.py
datadec/data.py
datadec/data_utils.py
datadec/df_utils.py
datadec/loader.py
datadec/model_utils.py
datadec/parsing.py
datadec/paths.py
datadec/pipeline.py
datadec/validation.py
datadec-0.1.0.dist-info/METADATA
datadec-0.1.0.dist-info/WHEEL
datadec-0.1.0.dist-info/RECORD
