Metadata-Version: 2.4
Name: datadec
Version: 0.1.0
Summary: A library to download and process DataDecide datasets from Hugging Face.
Author-email: Danielle Rothermel <danielle.rothermel@gmail.com>
Requires-Python: >=3.9
Requires-Dist: datasets>=4.0.0
Requires-Dist: dr-plotter>=0.1.0
Requires-Dist: huggingface-hub
Requires-Dist: ipykernel>=6.30.1
Requires-Dist: matplotlib>=3.9.4
Requires-Dist: numpy>=2.0.2
Requires-Dist: orjson>=3.11.2
Requires-Dist: pandas>=2.3.1
Requires-Dist: pyarrow>=21.0.0
